glasflow/__init__.py
glasflow/utils.py
glasflow/distributions/__init__.py
glasflow/distributions/resampled.py
glasflow/distributions/uniform.py
glasflow/flows/__init__.py
glasflow/flows/autoregressive.py
glasflow/flows/base.py
glasflow/flows/coupling.py
glasflow/flows/nsf.py
glasflow/flows/realnvp.py
glasflow/nets/__init__.py
glasflow/nets/mlp.py
glasflow/nflows/__init__.py
glasflow/nflows/version.py
glasflow/nflows/distributions/__init__.py
glasflow/nflows/distributions/base.py
glasflow/nflows/distributions/discrete.py
glasflow/nflows/distributions/mixture.py
glasflow/nflows/distributions/normal.py
glasflow/nflows/distributions/uniform.py
glasflow/nflows/flows/__init__.py
glasflow/nflows/flows/autoregressive.py
glasflow/nflows/flows/base.py
glasflow/nflows/flows/realnvp.py
glasflow/nflows/nn/__init__.py
glasflow/nflows/nn/nde/__init__.py
glasflow/nflows/nn/nde/made.py
glasflow/nflows/nn/nets/__init__.py
glasflow/nflows/nn/nets/mlp.py
glasflow/nflows/nn/nets/resnet.py
glasflow/nflows/transforms/__init__.py
glasflow/nflows/transforms/autoregressive.py
glasflow/nflows/transforms/base.py
glasflow/nflows/transforms/conv.py
glasflow/nflows/transforms/coupling.py
glasflow/nflows/transforms/linear.py
glasflow/nflows/transforms/lu.py
glasflow/nflows/transforms/made.py
glasflow/nflows/transforms/nonlinearities.py
glasflow/nflows/transforms/normalization.py
glasflow/nflows/transforms/orthogonal.py
glasflow/nflows/transforms/permutations.py
glasflow/nflows/transforms/qr.py
glasflow/nflows/transforms/reshape.py
glasflow/nflows/transforms/standard.py
glasflow/nflows/transforms/svd.py
glasflow/nflows/transforms/UMNN/__init__.py
glasflow/nflows/transforms/UMNN/autoregressive.py
glasflow/nflows/transforms/UMNN/coupling.py
glasflow/nflows/transforms/UMNN/monotonicnormalizer.py
glasflow/nflows/transforms/splines/__init__.py
glasflow/nflows/transforms/splines/cubic.py
glasflow/nflows/transforms/splines/linear.py
glasflow/nflows/transforms/splines/quadratic.py
glasflow-0.4.1.dist-info/LICENSE.md
glasflow-0.4.1.dist-info/METADATA
glasflow-0.4.1.dist-info/WHEEL
glasflow-0.4.1.dist-info/top_level.txt
glasflow-0.4.1.dist-info/RECORD
