Metadata-Version: 2.1
Name: glasflow
Version: 0.4.1
Summary: Normalising flows using nflows
Author: Jordan McGinn
Author-email: "Michael J. Williams" <michaeljw1@googlemail.com>, Federico Stachurski <f.stachurski.1@research.gla.ac.uk>, John Veitch <john.veitch@glasgow.ac.uk>
License: MIT
Project-URL: Homepage, https://github.com/uofgravity/glasflow
Keywords: normalising flows,normalizing flows,machine learning
Classifier: Programming Language :: Python :: 3
Classifier: License :: OSI Approved :: MIT License
Classifier: Operating System :: OS Independent
Requires-Python: >=3.8
License-File: LICENSE.md
Requires-Dist: numpy
Requires-Dist: torch>=1.11.0
Provides-Extra: dev
Requires-Dist: black[jupyter]; extra == "dev"
Requires-Dist: pre-commit; extra == "dev"
Requires-Dist: pytest; extra == "dev"
Requires-Dist: pytest-cov; extra == "dev"
Requires-Dist: pytest-integration; extra == "dev"
Requires-Dist: pytest-requires; extra == "dev"
Requires-Dist: pytest-rerunfailures; extra == "dev"
Provides-Extra: examples
Requires-Dist: ipykernel; extra == "examples"
Requires-Dist: matplotlib; extra == "examples"
Requires-Dist: scikit-learn; extra == "examples"
Requires-Dist: scipy; extra == "examples"
Requires-Dist: seaborn; extra == "examples"
Provides-Extra: nflows
Requires-Dist: nflows; extra == "nflows"
Provides-Extra: nflows-test
Requires-Dist: pytest; extra == "nflows-test"
Requires-Dist: pytest-rerunfailures; extra == "nflows-test"
Requires-Dist: torchtestcase; extra == "nflows-test"
Requires-Dist: UMNN; extra == "nflows-test"
